feagi_agent_freenove/ADC.py
feagi_agent_freenove/Led.py
feagi_agent_freenove/PCA9685.py
feagi_agent_freenove/__init__.py
feagi_agent_freenove/__main__.py
feagi_agent_freenove/configuration.py
feagi_agent_freenove/controller.py
feagi_agent_freenove/requirements.txt
feagi_agent_freenove/setup.sh
feagi_agent_freenove/verify.sh
feagi_agent_freenove/version.py
feagi_agent_freenove-0.0.19.dist-info/LICENSE
feagi_agent_freenove-0.0.19.dist-info/METADATA
feagi_agent_freenove-0.0.19.dist-info/WHEEL
feagi_agent_freenove-0.0.19.dist-info/top_level.txt
feagi_agent_freenove-0.0.19.dist-info/RECORD
