Metadata-Version: 2.1
Name: feagi_agent_freenove
Version: 0.0.19
Summary: Feagi agent freenove to connect feagi with your freenove_smartcar.
Home-page: https://github.com/feagi/feagi
Author: Neuraville INC
Author-email: info@feagi.org
Project-URL: Bug Tracker, https://github.com/feagi/feagi/issues
Classifier: Programming Language :: Python :: 3 :: Only
Classifier: License :: OSI Approved :: Apache Software License
Classifier: Operating System :: OS Independent
Requires-Python: >=3.6
License-File: LICENSE
Requires-Dist: feagi-agent
Requires-Dist: rpi-ws281x
Requires-Dist: RPi.GPIO
Requires-Dist: smbus
Requires-Dist: picamera
Requires-Dist: zmq >=0.0.0 ; python_version < "3.8"
